mcp_pokemon_server/__init__.py
mcp_pokemon_server/pokemon/__init__.py
mcp_pokemon_server/pokemon/mcp.py
mcp_pokemon_server-0.1.0.dist-info/METADATA
mcp_pokemon_server-0.1.0.dist-info/WHEEL
mcp_pokemon_server-0.1.0.dist-info/entry_points.txt
mcp_pokemon_server-0.1.0.dist-info/licenses/LICENSE
mcp_pokemon_server-0.1.0.dist-info/RECORD
